<?xml version="1.0" encoding="utf-8" ?>
<dwsync>
<file name="controller-first.gif" server="clients.pinecreekstudio.com/httpdocs/Accountalyst/" local="129458553600000000" remote="129496900200000000" />
<file name="controller-last.gif" server="clients.pinecreekstudio.com/httpdocs/Accountalyst/" local="129458553600000000" remote="129496900200000000" />
<file name="controller-next.gif" server="clients.pinecreekstudio.com/httpdocs/Accountalyst/" local="129458553600000000" remote="129496900200000000" />
<file name="controller-pause.gif" server="clients.pinecreekstudio.com/httpdocs/Accountalyst/" local="129458553600000000" remote="129496900200000000" />
<file name="controller-prev.gif" server="clients.pinecreekstudio.com/httpdocs/Accountalyst/" local="129458553600000000" remote="129496900200000000" />
<file name="controller.png" server="clients.pinecreekstudio.com/httpdocs/Accountalyst/" local="128416927840000000" remote="129496900200000000" />
<file name="loader-0.png" server="clients.pinecreekstudio.com/httpdocs/Accountalyst/" local="128539733880000000" remote="129496900200000000" />
<file name="loader-1.png" server="clients.pinecreekstudio.com/httpdocs/Accountalyst/" local="128539733280000000" remote="129496900200000000" />
<file name="loader-10.png" server="clients.pinecreekstudio.com/httpdocs/Accountalyst/" local="128539732180000000" remote="129496900200000000" />
<file name="loader-11.png" server="clients.pinecreekstudio.com/httpdocs/Accountalyst/" local="128539733420000000" remote="129496900200000000" />
<file name="loader-2.png" server="clients.pinecreekstudio.com/httpdocs/Accountalyst/" local="128539733760000000" remote="129496900200000000" />
<file name="loader-3.png" server="clients.pinecreekstudio.com/httpdocs/Accountalyst/" local="128539733580000000" remote="129496900200000000" />
<file name="loader-4.png" server="clients.pinecreekstudio.com/httpdocs/Accountalyst/" local="128539732760000000" remote="129496900200000000" />
<file name="loader-5.png" server="clients.pinecreekstudio.com/httpdocs/Accountalyst/" local="128539733040000000" remote="129496900200000000" />
<file name="loader-6.png" server="clients.pinecreekstudio.com/httpdocs/Accountalyst/" local="128539732600000000" remote="129496900200000000" />
<file name="loader-7.png" server="clients.pinecreekstudio.com/httpdocs/Accountalyst/" local="128539731900000000" remote="129496900200000000" />
<file name="loader-8.png" server="clients.pinecreekstudio.com/httpdocs/Accountalyst/" local="128539732900000000" remote="129496900200000000" />
<file name="loader-9.png" server="clients.pinecreekstudio.com/httpdocs/Accountalyst/" local="128539732360000000" remote="129496900200000000" />
<file name="slideshow.css" server="clients.pinecreekstudio.com/httpdocs/Accountalyst/" local="129497008114566199" remote="129496900200000000" />
</dwsync>